_spherepack.cp38-win_amd64.pyd
spharm/__init__.py
spharm/spharm.py
pyspharm_intel-1.1.1.dist-info/LICENSE.spherepack
pyspharm_intel-1.1.1.dist-info/METADATA
pyspharm_intel-1.1.1.dist-info/WHEEL
pyspharm_intel-1.1.1.dist-info/top_level.txt
pyspharm_intel-1.1.1.dist-info/RECORD
